pyttygif/__init__.py
pyttygif/__main__.py
pyttygif/capture.py
pyttygif/gifbuilder.py
pyttygif/ttyplay.py
pyttygif-0.3.3.dist-info/LICENSE
pyttygif-0.3.3.dist-info/METADATA
pyttygif-0.3.3.dist-info/WHEEL
pyttygif-0.3.3.dist-info/top_level.txt
pyttygif-0.3.3.dist-info/RECORD
