Metadata-Version: 2.1
Name: pyttygif
Version: 0.3.3
Summary: ttyrec to GIF converter
Home-page: https://github.com/tmp6154/pyttygif
Author: Vitaly Ostrosablin
Author-email: tmp6154@yandex.ru
Classifier: Development Status :: 4 - Beta
Classifier: Environment :: Console
Classifier: Intended Audience :: End Users/Desktop
Classifier: Programming Language :: Python :: 3 :: Only
Classifier: License :: OSI Approved :: GNU General Public License v3 (GPLv3)
Classifier: Operating System :: POSIX
Classifier: Topic :: Multimedia :: Graphics :: Capture :: Screen Capture
Classifier: Topic :: Terminals :: Terminal Emulators/X Terminals
License-File: LICENSE
